mmcifix/__init__.py
mmcifix/fixers.py
mmcifix/importance.py
mmcifix/util.py
mmcifix-0.4.0.dist-info/entry_points.txt
mmcifix-0.4.0.dist-info/WHEEL
mmcifix-0.4.0.dist-info/METADATA
mmcifix-0.4.0.dist-info/RECORD
