Metadata-Version: 2.1
Name: mmcifix
Version: 0.4.0
Summary: 
Author: Michael Milton
Author-email: michael.r.milton@gmail.com
Requires-Python: >=3.6.0,<4
Classifier: Programming Language :: Python :: 3
Classifier: Programming Language :: Python :: 3.6
Classifier: Programming Language :: Python :: 3.7
Classifier: Programming Language :: Python :: 3.8
Classifier: Programming Language :: Python :: 3.9
Requires-Dist: biopython (>=1.79,<2.0)
Requires-Dist: click (>=7.0.0,<8.0.0)
Requires-Dist: inflection (>=0.5.1,<0.6.0)
Requires-Dist: more-itertools (>=8.12.0,<9.0.0)
